bigamcp_bond_analysis/__init__.py
bigamcp_bond_analysis/server.py
bigamcp_bond_analysis/tools.py
bigamcp_bond_analysis-0.1.3.dist-info/METADATA
bigamcp_bond_analysis-0.1.3.dist-info/WHEEL
bigamcp_bond_analysis-0.1.3.dist-info/entry_points.txt
bigamcp_bond_analysis-0.1.3.dist-info/licenses/LICENSE
bigamcp_bond_analysis-0.1.3.dist-info/RECORD
