Metadata-Version: 2.4
Name: bigamcp-bond-analysis
Version: 0.1.3
Summary: A Model Context Protocol (MCP) server for convertible bond analysis using akshare data
Project-URL: Homepage, https://github.com/bigamcp/bigamcp-bond-analysis
Project-URL: Repository, https://github.com/bigamcp/bigamcp-bond-analysis
Project-URL: Issues, https://github.com/bigamcp/bigamcp-bond-analysis/issues
Project-URL: Documentation, https://github.com/bigamcp/bigamcp-bond-analysis#readme
Author-email: BigAMCP <bigamcp@example.com>
License: MIT
License-File: LICENSE
Keywords: akshare,convertible-bond,financial-analysis,mcp,model-context-protocol
Classifier: Development Status :: 4 - Beta
Classifier: Intended Audience :: Developers
Classifier: Intended Audience :: Financial and Insurance Industry
Classifier: License :: OSI Approved :: MIT License
Classifier: Programming Language :: Python :: 3
Classifier: Programming Language :: Python :: 3.10
Classifier: Programming Language :: Python :: 3.11
Classifier: Programming Language :: Python :: 3.12
Classifier: Programming Language :: Python :: 3.13
Classifier: Topic :: Office/Business :: Financial
Classifier: Topic :: Software Development :: Libraries :: Python Modules
Requires-Python: >=3.10
Requires-Dist: akshare>=1.14.0
Requires-Dist: mcp>=1.0.0
Requires-Dist: numpy>=1.24.0
Requires-Dist: pandas>=2.0.0
Requires-Dist: python-dateutil>=2.8.0
Provides-Extra: dev
Requires-Dist: black>=23.0.0; extra == 'dev'
Requires-Dist: mypy>=1.5.0; extra == 'dev'
Requires-Dist: pytest-asyncio>=0.21.0; extra == 'dev'
Requires-Dist: pytest>=7.0.0; extra == 'dev'
Requires-Dist: ruff>=0.1.0; extra == 'dev'
